myPackage/__init__.py
myPackage/somePython.py
testime/__init__.py
testime/somePython.py
testime-0.1.dist-info/METADATA
testime-0.1.dist-info/WHEEL
testime-0.1.dist-info/top_level.txt
testime-0.1.dist-info/RECORD
