Metadata-Version: 2.1
Name: testime
Version: 0.1
Summary: An example python package
Home-page: https://github.com/BillMills/python-package-example
Author: Bill Mills
Author-email: myemail@example.com
License: MIT
Platform: UNKNOWN
Requires-Dist: numpy
